yawigle/__init__.py
yawigle/yawigle.py
yawigle-0.0.4.dist-info/LICENSE
yawigle-0.0.4.dist-info/METADATA
yawigle-0.0.4.dist-info/WHEEL
yawigle-0.0.4.dist-info/top_level.txt
yawigle-0.0.4.dist-info/RECORD
