Metadata-Version: 2.1
Name: yawigle
Version: 0.0.4
Summary: Yet another Wigle.net client API
Home-page: https://github.com/yawigle/yawigle
Author: yawigle
Author-email: danilonc@users.noreply.github.com
License: UNKNOWN
Platform: UNKNOWN
Classifier: Programming Language :: Python :: 3
Classifier: License :: OSI Approved :: BSD License
Classifier: Development Status :: 3 - Alpha
Classifier: Topic :: Communications :: Ham Radio
Requires-Python: >=3.5.1
Requires-Dist: requests
